pg_index_insight/__init__.py
pg_index_insight/cli.py
pg_index_insight/database.py
pg_index_insight/queries.py
pg_index_insight/utils.py
pg_index_insight-1.5.0.dist-info/LICENSE
pg_index_insight-1.5.0.dist-info/METADATA
pg_index_insight-1.5.0.dist-info/WHEEL
pg_index_insight-1.5.0.dist-info/entry_points.txt
pg_index_insight-1.5.0.dist-info/top_level.txt
pg_index_insight-1.5.0.dist-info/RECORD
