Metadata-Version: 2.1
Name: pg_index_insight
Version: 1.5.0
Summary: A CLI tool for analyzing PostgreSQL index efficiency
Home-page: https://github.com/kylorend3r/pg_index_insight
Author: Huseyin Demir,Mert Yavaşca
Author-email: huseyin.d3r@gmail.com
Classifier: Programming Language :: Python :: 3
Classifier: License :: OSI Approved :: MIT License
Classifier: Operating System :: OS Independent
Requires-Python: >=3.6
License-File: LICENSE
Requires-Dist: click
Requires-Dist: psycopg2==2.9.9
Requires-Dist: tabulate
Requires-Dist: pyyaml
